pytower/__init__.py
pytower/pytower.py
pytower-0.0.1.dist-info/LICENSE
pytower-0.0.1.dist-info/METADATA
pytower-0.0.1.dist-info/WHEEL
pytower-0.0.1.dist-info/top_level.txt
pytower-0.0.1.dist-info/RECORD
