Metadata-Version: 2.1
Name: pytower
Version: 0.0.1
Summary: build and deploy Pythonic apps
Author-email: Salman Mohammadi <salman@pytower.com>
Project-URL: Homepage, https://pytower.com
Project-URL: Source Code, https://codeberg.org/pytower/pytower
Project-URL: Bug Tracker, https://codeberg.org/pytower/pytower/issues
Project-URL: Documentation, https://docs.pytower.com
Classifier: Programming Language :: Python :: 3
Classifier: License :: OSI Approved :: GNU Affero General Public License v3 or later (AGPLv3+)
Classifier: Operating System :: POSIX :: Linux
Classifier: Development Status :: 2 - Pre-Alpha
Classifier: Environment :: Web Environment
Classifier: Intended Audience :: Developers
Requires-Python: >=3.8
License-File: LICENSE
